{
  "13": {
    "file": "source/13.gif",
    "dir": "",
    "widths": [
      320
    ],
    "alt": "",
    "caption": "",
    "generated": true,
    "orig_width": 556,
    "orig_height": 313
  },
  "logo2": {
    "file": "source/logo2.png",
    "dir": "",
    "widths": [
      320,
      640
    ],
    "alt": "Логотип Гефест",
    "caption": "",
    "generated": true
  },
  "data_179": {
    "file": "source/data_179.jpg",
    "dir": "",
    "widths": [
      320
    ],
    "alt": "",
    "caption": "",
    "generated": true,
    "orig_width": 455,
    "orig_height": 481
  },
  "data_180": {
    "file": "source/data_180.jpg",
    "dir": "",
    "widths": [
      320
    ],
    "alt": "",
    "caption": "",
    "generated": true,
    "orig_width": 336,
    "orig_height": 370
  },
  "bgbg": {
    "file": "source/bgbg.gif",
    "dir": "",
    "widths": [
      320,
      640,
      1024
    ],
    "alt": "",
    "caption": "",
    "generated": true,
    "orig_width": 1048,
    "orig_height": 1150
  },
  "gilin": {
    "file": "source/gilin.jpg",
    "dir": "",
    "widths": [
      320
    ],
    "alt": "",
    "caption": "",
    "generated": true,
    "orig_width": 455,
    "orig_height": 481
  },
  "logo": {
    "file": "source/logo.png",
    "dir": "",
    "widths": [
      320,
      640,
      1024,
      1600
    ],
    "alt": "",
    "caption": "",
    "generated": true,
    "orig_width": 2471,
    "orig_height": 2471
  },
  "pic1": {
    "file": "source/pic1.webp",
    "dir": "",
    "widths": [
      320,
      640,
      1024,
      1600
    ],
    "alt": "",
    "caption": "",
    "generated": true,
    "orig_width": 1920,
    "orig_height": 1080
  },
  "pic2": {
    "file": "source/pic2.webp",
    "dir": "",
    "widths": [
      320,
      640,
      1024,
      1600
    ],
    "alt": "",
    "caption": "",
    "generated": true,
    "orig_width": 1920,
    "orig_height": 1080
  },
  "pic3": {
    "file": "source/pic3.webp",
    "dir": "",
    "widths": [
      320,
      640,
      1024,
      1600
    ],
    "alt": "",
    "caption": "",
    "generated": true,
    "orig_width": 1920,
    "orig_height": 1080
  },
  "pic4": {
    "file": "source/pic4.webp",
    "dir": "",
    "widths": [
      320,
      640,
      1024,
      1600
    ],
    "alt": "",
    "caption": "",
    "generated": true,
    "orig_width": 1920,
    "orig_height": 1080
  },
  "pic5": {
    "file": "source/pic5.webp",
    "dir": "",
    "widths": [
      320,
      640,
      1024,
      1600
    ],
    "alt": "",
    "caption": "",
    "generated": true,
    "orig_width": 1920,
    "orig_height": 1080
  },
  "proscirnov": {
    "file": "source/proscirnov.jpg",
    "dir": "",
    "widths": [
      320
    ],
    "alt": "",
    "caption": "",
    "generated": true,
    "orig_width": 336,
    "orig_height": 370
  },
  "prosvirnov": {
    "file": "source/prosvirnov.jpg",
    "dir": "",
    "widths": [
      320
    ],
    "alt": "",
    "caption": "",
    "generated": true,
    "orig_width": 336,
    "orig_height": 370
  }
}
